rpmdeplint/__init__.py
rpmdeplint/analyzer.py
rpmdeplint/cli.py
rpmdeplint/repodata.py
rpmdeplint-2.0.dist-info/METADATA
rpmdeplint-2.0.dist-info/WHEEL
rpmdeplint-2.0.dist-info/entry_points.txt
rpmdeplint-2.0.dist-info/licenses/COPYING
rpmdeplint-2.0.dist-info/RECORD
